filtersignals/__init__.py
django_filtersignals-0.2.dist-info/LICENSE
django_filtersignals-0.2.dist-info/METADATA
django_filtersignals-0.2.dist-info/WHEEL
django_filtersignals-0.2.dist-info/top_level.txt
django_filtersignals-0.2.dist-info/RECORD
